MANIFEST.in
README
green-app.json
lambda_function.py
setup.cfg
setup.py
green_example.egg-info/PKG-INFO
green_example.egg-info/SOURCES.txt
green_example.egg-info/dependency_links.txt
green_example.egg-info/requires.txt
green_example.egg-info/top_level.txt